filelib/__init__.py
filelib/client.py
filelib/exceptions.py
filelib/multifile.py
filelibpy-0.0.71.data/scripts/filelib
filelibpy-0.0.71.data/scripts/filelibx
filelibpy-0.0.71.dist-info/LICENSE
filelibpy-0.0.71.dist-info/METADATA
filelibpy-0.0.71.dist-info/WHEEL
filelibpy-0.0.71.dist-info/top_level.txt
filelibpy-0.0.71.dist-info/RECORD
