Metadata-Version: 2.1
Name: filelibpy
Version: 0.0.71
Summary: Filelib official python package for Filelib API
Home-page: https://github.com/filelib/filelib-python
Author: filelib
Author-email: 
License: UNKNOWN
Platform: UNKNOWN
Classifier: Development Status :: 3 - Alpha
Classifier: License :: OSI Approved :: MIT License
Classifier: Operating System :: OS Independent
Classifier: Programming Language :: Python :: 3.5
Classifier: Programming Language :: Python :: 3.6
Classifier: Programming Language :: Python :: 3.7
Requires-Python: >=3.5
Requires-Dist: requests (==2.21.0)
Requires-Dist: PyJWT (==1.7.1)
Requires-Dist: pytz (==2019.1)
